{
  "products": [
    {
      "product_id": "ble1",
      "product_title": "Figura de Anime Bleach Ichigo Kurosaki, Guerra de los Mil Anos, Estatua Coleccionable PVC",
      "product_main_image_url": "https://cdn.myanimelist.net/images/anime/1908/135431l.jpg",
      "original_price": "39.99",
      "sale_price": "18.80",
      "discount": "53%",
      "evaluate_rate": "4.7",
      "lastest_volume": 280,
      "product_detail_url": "https://s.click.aliexpress.com/e/_c3ia2riT",
      "promotion_link": "https://s.click.aliexpress.com/e/_c3ia2riT"
    },
    {
      "product_id": "ble2",
      "product_title": "Caja Sorpresa de Figuras de Anime BLEACH, Juguete Coleccionable Aleatorio",
      "product_main_image_url": "https://cdn.myanimelist.net/images/anime/1908/135431l.jpg",
      "original_price": "7.01",
      "sale_price": "7.01",
      "discount": "0%",
      "evaluate_rate": "4.3",
      "lastest_volume": 340,
      "product_detail_url": "https://s.click.aliexpress.com/e/_c3J97qSR",
      "promotion_link": "https://s.click.aliexpress.com/e/_c3J97qSR"
    },
    {
      "product_id": "ble3",
      "product_title": "Dasin Bleach Kurosaki Ichigo Aizen Sousuke SHF Figura de Accion",
      "product_main_image_url": "https://cdn.myanimelist.net/images/anime/1908/135431l.jpg",
      "original_price": "88.25",
      "sale_price": "62.66",
      "discount": "29%",
      "evaluate_rate": "4.9",
      "lastest_volume": 150,
      "product_detail_url": "https://s.click.aliexpress.com/e/_c4SxiKxt",
      "promotion_link": "https://s.click.aliexpress.com/e/_c4SxiKxt"
    },
    {
      "product_id": "ble4",
      "product_title": "Figura de Accion de Toshiro Hitsugaya de 28 cm, Estatua GK de Anime Bleach",
      "product_main_image_url": "https://cdn.myanimelist.net/images/anime/1908/135431l.jpg",
      "original_price": "79.38",
      "sale_price": "42.07",
      "discount": "47%",
      "evaluate_rate": "4.6",
      "lastest_volume": 110,
      "product_detail_url": "https://s.click.aliexpress.com/e/_c3RQ6oj1",
      "promotion_link": "https://s.click.aliexpress.com/e/_c3RQ6oj1"
    },
    {
      "product_id": "ble5",
      "product_title": "Figura de accion de anime Bleach de 33 cm, Final Getsuga Mugetsu",
      "product_main_image_url": "https://cdn.myanimelist.net/images/anime/1908/135431l.jpg",
      "original_price": "163.21",
      "sale_price": "89.77",
      "discount": "45%",
      "evaluate_rate": "4.8",
      "lastest_volume": 90,
      "product_detail_url": "https://s.click.aliexpress.com/e/_c3X8J1th",
      "promotion_link": "https://s.click.aliexpress.com/e/_c3X8J1th"
    },
    {
      "product_id": "ble6",
      "product_title": "Camisetas de Anime Kurosaki Ichigo Bleach, Camiseta Vintage Algodon",
      "product_main_image_url": "https://cdn.myanimelist.net/images/anime/1908/135431l.jpg",
      "original_price": "21.23",
      "sale_price": "21.23",
      "discount": "0%",
      "evaluate_rate": "4.2",
      "lastest_volume": 180,
      "product_detail_url": "https://s.click.aliexpress.com/e/_c4T82RaT",
      "promotion_link": "https://s.click.aliexpress.com/e/_c4T82RaT"
    },
    {
      "product_id": "ble7",
      "product_title": "Bleach Shf Kurosaki Ichigo modelo con alambre de hierro, guerra mil anos",
      "product_main_image_url": "https://cdn.myanimelist.net/images/anime/1908/135431l.jpg",
      "original_price": "25.50",
      "sale_price": "25.50",
      "discount": "0%",
      "evaluate_rate": "4.5",
      "lastest_volume": 65,
      "product_detail_url": "https://s.click.aliexpress.com/e/_c31PW2bD",
      "promotion_link": "https://s.click.aliexpress.com/e/_c31PW2bD"
    }
  ],
  "updatedAt": "2026-07-12T00:00:00Z",
  "category": "bleach"
}